{"event_id": "5d9722a94333435cb3ebf46356ddc5d7", "project_id": "2", "level": "error", "release": "1.0.0", "context": {"os": "Windows 11", "java_version": "17.0.18", "runtime": "java"}, "client": {"sdk": "tracelify.java"}, "error": {"stacktrace": "java.lang.ArithmeticException: / by zero\r\n	at com.tracelify.Test.main(Test.java:23)\r\n", "type": "ArithmeticException", "message": "/ by zero"}, "user": {"id": "user_101"}, "breadcrumbs": [{"message": "App started"}, {"message": "User clicked button"}], "timestamp": "2026-04-04T16:54:44.000911Z", "tags": {"env": "Production"}}
✅ Done
